ns_jwt/__init__.py
ns_jwt/ns_jwt.py
ns_jwt-0.1.4.dist-info/LICENSE
ns_jwt-0.1.4.dist-info/METADATA
ns_jwt-0.1.4.dist-info/WHEEL
ns_jwt-0.1.4.dist-info/top_level.txt
ns_jwt-0.1.4.dist-info/RECORD
