Metadata-Version: 2.1
Name: ns-jwt
Version: 0.1.4
Summary: Notary Service support for JWT
Home-page: https://github.com/RENCI-NRIG/notary-service
Author: Ilya Baldin
Author-email: ibaldin@renci.org
License: MIT
Platform: UNKNOWN
Classifier: Programming Language :: Python :: 3
Classifier: License :: OSI Approved :: MIT License
Classifier: Operating System :: OS Independent
License-File: LICENSE
Requires-Dist: PyJWT
Requires-Dist: cryptography
Requires-Dist: python-dateutil
